[{
    "id": "arpm",
    "title": "Soft Tissues",
    "content": [
        {
            "title": "",
            "image": [
                {
                    "url": "assets/images/radiological-anatomy/en/1.jpg", 
                    "subtitle": "Mammary symmetry (arrows)."
                }
            ],
            "description": ["<br><b>What should we look for and evaluate?</b><br><br>1- Symmetry evaluation (transparency)<br>2- Breast evaluation, subcutaneous tissue, cutaneous folds, cervical region (position of the trachea) and scapular region.<br>3- Discard subcutaneous emphysema, wall injury versus parenchymal lesion."],
            "studyKeys": [],
            "reference": []
        },
        {
            "title": "",
            "image": [
                {
                    "url": "assets/images/radiological-anatomy/en/2.jpg", 
                    "subtitle": ""
                }
            ],
            "description": ["<br><b>What should we look for and evaluate?</b><br><br>1- Symmetry evaluation (transparency)<br>2- Breast evaluation, subcutaneous tissue, cutaneous folds, cervical region (position of the trachea) and scapular region.<br>3- Discard subcutaneous emphysema, wall injury versus parenchymal lesion."],
            "studyKeys": [],
            "reference": []
        }
    ]
},
{
    "id": "arao",
    "title": "Bone Structure",
    "content": [
        {
            "title": "",
            "image": [
                {
                    "url": "assets/images/radiological-anatomy/en/3.jpg", 
                    "subtitle": "Anterior ribs."
                },
                {
                    "url": "assets/images/radiological-anatomy/en/4.jpg", 
                    "subtitle": "Posterior ribs."
                }
            ],
            "description": [],
            "studyKeys": [],
            "reference": []
        },
        {
            "title": "",
            "image": [
                {
                    "url": "assets/images/radiological-anatomy/en/5.jpg",
                    "subtitle": "Clavicles: right (blue arrow) and left (green arrow) normopositioned in PA radiography."
                }
            ],
            "description": [],
            "studyKeys": [],
            "reference": []
        },
        {
            "title": "",
            "image": [
                {
                    "url": "assets/images/radiological-anatomy/en/6.jpg",
                    "subtitle": "Sternum."
                },
                {
                    "url": "assets/images/radiological-anatomy/en/7.jpg",
                    "subtitle": "Vertebral bodies."
                }
            ],
            "description": [],
            "studyKeys": [],
            "reference": []
        }
    ]
},
{
    "id": "ardp",
    "title": "Diaphragm and Pleural Space",
    "content": [
        {
            "title": "",
            "image": [
                {
                    "url": "assets/images/radiological-anatomy/en/8.jpg", 
                    "subtitle": "Diaphragm"
                }
            ],
            "description": ["95% RIGHT side is higher, because of the hepatic structure.",
                            "RIGHT is continuous.",
                            "LEFT is not displayed due to contact with the heart."],
            "studyKeys": [],
            "reference": []
        },
        {
            "title": "",
            "image": [
                {
                    "url": "assets/images/radiological-anatomy/en/9.jpg",
                    "subtitle": ""
                }
            ],
            "description": ["95% RIGHT side is higher, because of the hepatic structure.",
                            "RIGHT is continuous.",
                            "LEFT is not displayed due to contact with the heart.",
                            "* Attention to costophrenic sinuses that should be free"],
            "studyKeys": [],
            "reference": []
        }
    ]
},
{
    "id": "arf",
    "title": "Fissures",
    "content": [
        {
            "title": "",
            "image": [
                {
                    "url": "assets/images/radiological-anatomy/en/10.jpg", 
                    "subtitle": "X-rays PA and profile showing:"
                }
            ],
            "description": ["Horizontal Fissure of the Right Lung (Yellow Line).",
                            "Horizontal and Oblique Fissures seen in Profile (Yellow and Red Line)."],
            "studyKeys": [],
            "reference": []
        },
        {
            "title": "",
            "image": [
                {
                    "url": "assets/images/radiological-anatomy/en/11.jpg",
                    "subtitle": "Profile X-ray showing the Oblique Fissure (yellow line) dividing the left lung into upper and lower lobes."
                }
            ],
            "description": [],
            "studyKeys": [],
            "reference": []
        }
    ]
},
{
    "id": "arl",
    "title": "Lobes",
    "summary": {
        "columns": [
            {
                "title": "Right Lung",
                "items": [
                    {
                        "title": "Upper Lobe",
                        "slide": 1
                    },
                    {
                        "title": "Middle Lobe",
                        "slide": 2
                    },
                    {
                        "title": "Lower Lobe",
                        "slide": 3
                    }
                ]
            },
            {
                "title": "Left Lung",
                "items": [
                    {
                        "title": "Upper Lobe",
                        "slide": 4
                    },
                    {
                        "title": "Lower Lobe",
                        "slide": 5
                    }
                ]
            }
        ]
    },
    "content": [
        {
            "title": "",
            "image": [
                {
                    "url": "assets/images/radiological-anatomy/en/12.jpg", 
                    "subtitle": "Right Upper Lobe"
                }
            ],
            "description": [],
            "studyKeys": [],
            "reference": []
        },
        {
            "title": "",
            "image": [
                {
                    "url": "assets/images/radiological-anatomy/en/13.jpg",
                    "subtitle": "Right Middle Lobe"
                }
            ],
            "description": [],
            "studyKeys": [],
            "reference": []
        },
        {
            "title": "",
            "image": [
                {
                    "url": "assets/images/radiological-anatomy/en/14.jpg",
                    "subtitle": "Right Lower Lobe"
                }
            ],
            "description": [],
            "studyKeys": [],
            "reference": []
        },
        {
            "title": "",
            "image": [
                {
                    "url": "assets/images/radiological-anatomy/en/15.jpg",
                    "subtitle": "Left Upper Lobe"
                }
            ],
            "description": [],
            "studyKeys": [],
            "reference": []
        },
        {
            "title": "",
            "image": [
                {
                    "url": "assets/images/radiological-anatomy/en/16.jpg",
                    "subtitle": "Left Lower Lobe"
                }
            ],
            "description": [],
            "studyKeys": [],
            "reference": []
        }
    ]
},
{
    "id": "ars",
    "title": "Segmentation",
    "summary": {
        "columns": [
            {
                "title": "Right Lung",
                "items": [
                    {
                        "title": "Apical (N°1)",
                        "slide": 1
                    },
                    {
                        "title": "Anterior (N°2)",
                        "slide": 2
                    },
                    {
                        "title": "Posterior (N°3)",
                        "slide": 3
                    },
                    {
                        "title": "Lateral (N°4)",
                        "slide": 4
                    },
                    {
                        "title": "Medial (N°5)",
                        "slide": 5
                    },
                    {
                        "title": "Apical (superior N°6)",
                        "slide": 6
                    },
                    {
                        "title": "Basal Medial (N°7)",
                        "slide": 7
                    },
                    {
                        "title": "Basal Anterior (N°8)",
                        "slide": 8
                    },
                    {
                        "title": "Basal Lateral (N°9)",
                        "slide": 9
                    },
                    {
                        "title": "Basal Posterior (N°10)",
                        "slide": 10
                    }
                ]
            },
            {
                "title": "Left Lung",
                "items": [
                    {
                        "title": "Posterior Apical (N°1 e N°3)",
                        "slide": 11
                    },
                    {
                        "title": "Anterior (Nº2)",
                        "slide": 12
                    },
                    {
                        "title": "Lingular Superior (Nº4)",
                        "slide": 13
                    },
                    {
                        "title": "Lingular Inferior (Nº5)",
                        "slide": 14
                    },
                    {
                        "title": "Apical (Superior Nº6)",
                        "slide": 15
                    },
                    {
                        "title": "Basal Ântero-Medial (N°7 e N°8)",
                        "slide": 16
                    },
                    {
                        "title": "Basal Lateral (Nº9)",
                        "slide": 17
                    },
                    {
                        "title": "Basal Posterior (Nº10)",
                        "slide": 18
                    }
                ]
            }
        ]
    },
    "content": [
        {
            "title": "",
            "image": [
                {
                    "url": "assets/images/radiological-anatomy/en/17.jpg",
                    "subtitle": "Upper right lobe apical segment. (Segment Nº1)"
                }
            ],
            "description": [],
            "studyKeys": [],
            "reference": []
        },
        {
            "title": "",
            "image": [
                {
                    "url": "assets/images/radiological-anatomy/en/18.jpg",
                    "subtitle": "Anterior segment of the right upper lobe. (Segment Nº2)"
                }
            ],
            "description": [],
            "studyKeys": [],
            "reference": []
        },
        {
            "title": "",
            "image": [
                {
                    "url": "assets/images/radiological-anatomy/en/19.jpg",
                    "subtitle": "Posterior segment of the right upper lobe. (Segment Nº3)"
                }
            ],
            "description": [],
            "studyKeys": [],
            "reference": []
        },
        {
            "title": "",
            "image": [
                {
                    "url": "assets/images/radiological-anatomy/en/20.jpg",
                    "subtitle": "Lateral segment of the middle lobe. (Segment Nº4)"
                }
            ],
            "description": [],
            "studyKeys": [],
            "reference": []
        },
        {
            "title": "",
            "image": [
                {
                    "url": "assets/images/radiological-anatomy/en/21.jpg",
                    "subtitle": "Medial segment of the middle lobe. (Segment Nº5)"
                }
            ],
            "description": [],
            "studyKeys": [],
            "reference": []
        },
        {
            "title": "",
            "image": [
                {
                    "url": "assets/images/radiological-anatomy/en/22.jpg",
                    "subtitle": "Upper segment of the right lower lobe. (Segment Nº6)"
                }
            ],
            "description": [],
            "studyKeys": [],
            "reference": []
        },
        {
            "title": "",
            "image": [
                {
                    "url": "assets/images/radiological-anatomy/en/23.jpg",
                    "subtitle": "Middle segment of the lower right lobe. (Segment Nº7)"
                }
            ],
            "description": [],
            "studyKeys": [],
            "reference": []
        },
        {
            "title": "",
            "image": [
                {
                    "url": "assets/images/radiological-anatomy/en/24.jpg",
                    "subtitle": "Anterior segment of the lower right lobe. (Segment Nº8)"
                }
            ],
            "description": [],
            "studyKeys": [],
            "reference": []
        },
        {
            "title": "",
            "image": [
                {
                    "url": "assets/images/radiological-anatomy/en/25.jpg",
                    "subtitle": "Lateral segment of the lower right lobe. (Segment Nº9)"
                }
            ],
            "description": [],
            "studyKeys": [],
            "reference": []
        },
        {
            "title": "",
            "image": [
                {
                    "url": "assets/images/radiological-anatomy/en/26.jpg",
                    "subtitle": "Posterior segment of the lower right lobe. (Segment Nº10)"
                }
            ],
            "description": [],
            "studyKeys": [],
            "reference": []
        },
        {
            "title": "",
            "image": [
                {
                    "url": "assets/images/radiological-anatomy/en/27.jpg",
                    "subtitle": "Apical segment (No. 1) and posterior (No.3) of the upper left lobe. (Segment Nº1 e Nº3)"
                }
            ],
            "description": [],
            "studyKeys": [],
            "reference": []
        },
        {
            "title": "",
            "image": [
                {
                    "url": "assets/images/radiological-anatomy/en/28.jpg",
                    "subtitle": "Anterior segment of the upper left lobe. (Segment Nº2)"
                }
            ],
            "description": [],
            "studyKeys": [],
            "reference": []
        },
        {
            "title": "",
            "image": [
                {
                    "url": "assets/images/radiological-anatomy/en/29.jpg",
                    "subtitle": "Upper lingular segment of the upper left lobe. (Segment Nº4)"
                }
            ],
            "description": [],
            "studyKeys": [],
            "reference": []
        },
        {
            "title": "",
            "image": [
                {
                    "url": "assets/images/radiological-anatomy/en/30.jpg",
                    "subtitle": "Lower lingular segment of the upper left lobe. (Segment Nº5)"
                }
            ],
            "description": [],
            "studyKeys": [],
            "reference": []
        },
        {
            "title": "",
            "image": [
                {
                    "url": "assets/images/radiological-anatomy/en/31.jpg",
                    "subtitle": "Upper segment of the lower left lobe. (Segmeno Nº6)"
                }
            ],
            "description": [],
            "studyKeys": [],
            "reference": []
        },
        {
            "title": "",
            "image": [
                {
                    "url": "assets/images/radiological-anatomy/en/32.jpg",
                    "subtitle": "Anteromedial segment  (antero = No. 8 and  medial = No. 7) of the lower left lobe. (Segment Nº7 e N°8)"
                }
            ],
            "description": [],
            "studyKeys": [],
            "reference": []
        },
        {
            "title": "",
            "image": [
                {
                    "url": "assets/images/radiological-anatomy/en/33.jpg",
                    "subtitle": "Lateral segment of the lower left lobe. (Segment Nº9)"
                }
            ],
            "description": [],
            "studyKeys": [],
            "reference": []
        },
        {
            "title": "",
            "image": [
                {
                    "url": "assets/images/radiological-anatomy/en/34.jpg",
                    "subtitle": "Posterior segment of the lower left lobe. (Segment Nº10)"
                }
            ],
            "description": [],
            "studyKeys": [],
            "reference": []
        }
    ]
},
{
    "id": "arth",
    "title": "Trachea and Hilum",
    "content": [
        {
            "title": "",
            "image": [
                {
                    "url": "assets/images/radiological-anatomy/en/35.jpg", 
                    "subtitle": "Trachea (blue arrows) and hilum (red arrows)."
                }
            ],
            "description": [],
            "studyKeys": [],
            "reference": []
        },
        {
            "title": "",
            "image": [
                {
                    "url": "assets/images/radiological-anatomy/en/36.jpg",
                    "subtitle": "Trachea (outlined by red lines)."
                }
            ],
            "description": [],
            "studyKeys": [],
            "reference": []
        }
    ]
},
{
    "id": "artcgv",
    "title": "Heart and Great Vessels",
    "content": [
        {
            "title": "",
            "image": [
                {
                    "url": "assets/images/radiological-anatomy/en/37.jpg", 
                    "subtitle": ""
                }
            ],
            "description": [],
            "studyKeys": [],
            "reference": []
        }
    ]
},
{
    "id": "arm",
    "title": "Mediastinum",
    "content": [
        {
            "title": "",
            "image": [
                {
                    "url": "assets/images/radiological-anatomy/en/38.jpg", 
                    "subtitle": ""
                }
            ],
            "description": ["<br><br><b>Schematic division of the mediastinum proposed by ITMIG (2017)</b><br><br>Prevascular – Anterior<br>Superior: thoracic inlet. Inferior: diaphragmAnterior: sternum. Lateral: parietal mediastinal pleura. Posterior: anterior aspect of the pericardium as it wraps around the heart in a curvilinear fashion.<br><br>Visceral –Medial<br>Superior: thoracic inlet. Inferior: diaphragm. Anterior: posterior boundaries of the prevascular compartment. Posterior: vertical line connecting a point on each thoracic vertebral body 1 cm posterior to its anterior margin.<br><br>Paravertebral – Posterior<br>Superior: thoracic inlet. Inferior: diaphragm. Anterior: posterior boundaries of the visceral compartment. Posterolateral: vertical line against the posterior margin of the chest wall at the lateral margin of the transverse process of the thoracic spine."],
            "studyKeys": [],
            "reference": ["Reference: Carter et al. ITMIG Classification of Mediastinal Compartments and Multidisciplinary Approach to Mediastinal Masses. RadioGraphics 2017; 37:0000–0000"]
        }
    ]
}]